pyservicebinding/__init__.py
pyservicebinding/binding.py
pyservicebinding/binding_test.py
pyservicebinding-0.3.0.dist-info/LICENSE
pyservicebinding-0.3.0.dist-info/METADATA
pyservicebinding-0.3.0.dist-info/WHEEL
pyservicebinding-0.3.0.dist-info/entry_points.txt
pyservicebinding-0.3.0.dist-info/top_level.txt
pyservicebinding-0.3.0.dist-info/RECORD
