Metadata-Version: 2.1
Name: pyservicebinding
Version: 0.3.0
Summary: Kubernetes Service Binding Library for Python Applications
Home-page: https://github.com/baijum/pyservicebinding
Author: Baiju Muthukadan
Author-email: baiju.m.mail@gmail.com
License: UNKNOWN
Project-URL: Bug Tracker, https://github.com/baijum/pyservicebinding/issues
Platform: UNKNOWN
Classifier: Programming Language :: Python :: 3.8
Classifier: License :: OSI Approved :: Apache Software License
Classifier: Operating System :: OS Independent
Requires-Python: >=3.8
License-File: LICENSE
Requires-Dist: PyYAML
